pandasnet/__init__.py
pandasnet/libs/PandasNet.deps.json
pandasnet/libs/PandasNet.dll
pandasnet/libs/PandasNet.pdb
pandasnet-1.0.dist-info/LICENSE
pandasnet-1.0.dist-info/METADATA
pandasnet-1.0.dist-info/WHEEL
pandasnet-1.0.dist-info/top_level.txt
pandasnet-1.0.dist-info/RECORD
