Metadata-Version: 2.1
Name: pandasnet
Version: 1.0
Summary: Extensions of pythonnet package to support pandas DataFrame conversions
Home-page: https://github.com/fdieulle/pandasnet
Author: Fabien Dieulle
Author-email: fabiendieulle@hotmail.fr
Classifier: License :: OSI Approved :: MIT License
Classifier: Programming Language :: C#
Classifier: Programming Language :: Python :: 3
Classifier: Programming Language :: Python :: 3.6
Classifier: Programming Language :: Python :: 3.7
Classifier: Programming Language :: Python :: 3.8
Classifier: Programming Language :: Python :: 3.9
Classifier: Programming Language :: Python :: 3.10
Classifier: Programming Language :: Python :: 3.11
Classifier: Operating System :: Microsoft :: Windows
Classifier: Operating System :: POSIX :: Linux
Classifier: Operating System :: MacOS :: MacOS X
License-File: LICENSE
Requires-Dist: pycparser
Requires-Dist: pythonnet
Requires-Dist: pandas
